qwen3tts/__init__.py
qwen3tts/client.py
qwen3_tts_app-1.0.2.dist-info/METADATA
qwen3_tts_app-1.0.2.dist-info/WHEEL
qwen3_tts_app-1.0.2.dist-info/top_level.txt
qwen3_tts_app-1.0.2.dist-info/RECORD
